saikitz/__init__.py
saikitz/_chatollama.py
saikitz/aikit.py
saikitz/toolist.py
saikitz/utils.py
saikitz/prompts/chiprompt.txt
saikitz/prompts/opmprompt.txt
saikitz/prompts/sysprompt.txt
saikitz/prompts/transprompt.txt
saikitz-0.2.1.dist-info/METADATA
saikitz-0.2.1.dist-info/WHEEL
saikitz-0.2.1.dist-info/licenses/LICENSE
saikitz-0.2.1.dist-info/RECORD
