Metadata-Version: 2.3
Name: saikitz
Version: 0.2.1
Summary: saiKitz: Sidney Zhang's Toolkit for AI Conversations & Info Queries
Author-email: Sidney Zhang <liangyi@me.com>
License: MulanPSL-2.0
Requires-Python: >=3.8
Requires-Dist: ipython>=8.29.0
Requires-Dist: openai>=1.55.1
